SteamedBread/__init__.py
SteamedBread/BrowseTools/BrowserFormat.py
SteamedBread/BrowseTools/__init__.py
SteamedBread/ConfigTools/Config.py
SteamedBread/ConfigTools/__init__.py
SteamedBread/DecoratorTools/DecoratorParameterize.py
SteamedBread/DecoratorTools/__init__.py
SteamedBread/EmailTools/EmailFormat.py
SteamedBread/EmailTools/__init__.py
SteamedBread/ExceptionTools/ExceptionCatch.py
SteamedBread/ExceptionTools/__init__.py
SteamedBread/ExpectTools/ExpectFormat.py
SteamedBread/ExpectTools/__init__.py
SteamedBread/FileTools/FileOperateFormat.py
SteamedBread/FileTools/__init__.py
SteamedBread/LoggerTools/Logger.py
SteamedBread/LoggerTools/__init__.py
SteamedBread/RequestTools/HttpRequest.py
SteamedBread/RequestTools/__init__.py
SteamedBread/SingletonTools/Singleton.py
SteamedBread/SingletonTools/__init__.py
SteamedBread/TimeTools/TimeFormat.py
SteamedBread/TimeTools/__init__.py
SteamedBread/poium/__init__.py
SteamedBread/poium/config.py
SteamedBread/poium/javascript.py
SteamedBread/poium/selenium.py
SteamedBread/poium/webdriver.py
SteamedBread/poium/processing/__init__.py
SteamedBread/poium/universal/__init__.py
SteamedBread/poium/universal/exceptions.py
SteamedBread/poium/universal/selector.py
SteamedBun/__init__.py
SteamedBun/BrowseTools/BrowserFormat.py
SteamedBun/BrowseTools/__init__.py
SteamedBun/ConfigTools/Config.py
SteamedBun/ConfigTools/__init__.py
SteamedBun/DecoratorTools/DecoratorParameterize.py
SteamedBun/DecoratorTools/__init__.py
SteamedBun/EmailTools/EmailFormat.py
SteamedBun/EmailTools/__init__.py
SteamedBun/ExceptionTools/ExceptionCatch.py
SteamedBun/ExceptionTools/__init__.py
SteamedBun/ExpectTools/ExpectFormat.py
SteamedBun/ExpectTools/__init__.py
SteamedBun/FileTools/FileOperateFormat.py
SteamedBun/FileTools/__init__.py
SteamedBun/LoggerTools/Logger.py
SteamedBun/LoggerTools/__init__.py
SteamedBun/RequestTools/HttpRequest.py
SteamedBun/RequestTools/__init__.py
SteamedBun/SingletonTools/Singleton.py
SteamedBun/SingletonTools/__init__.py
SteamedBread-0.1.0.dist-info/METADATA
SteamedBread-0.1.0.dist-info/WHEEL
SteamedBread-0.1.0.dist-info/top_level.txt
SteamedBread-0.1.0.dist-info/RECORD
