Metadata-Version: 2.1
Name: SteamedBread
Version: 0.1.0
Summary: 馒头的第三方库
Home-page: https://github.com/neihanshenshou/SteamedBun.git
Author: 馒头
Author-email: neihanshenshou@163.com
License: MIT
Platform: MacOS、Window
Requires-Dist: allure-pytest (==2.10.0)
Requires-Dist: colorama (==0.4.6)
Requires-Dist: func-timeout (==4.3.5)
Requires-Dist: openpyxl (==2.6.4)
Requires-Dist: pandas (==1.4.4)
Requires-Dist: Pillow (==9.5.0)
Requires-Dist: python-dateutil (==2.8.2)
Requires-Dist: pytest (==7.1.2)
Requires-Dist: PyYAML (==6.0)
Requires-Dist: requests (==2.30.0)
Requires-Dist: selenium (==4.4.3)
Requires-Dist: urllib3 (==1.26.12)
